SSD/SSD.py
SSD/__init__.py
SSD_python-0.0.1.dist-info/LICENSE
SSD_python-0.0.1.dist-info/METADATA
SSD_python-0.0.1.dist-info/WHEEL
SSD_python-0.0.1.dist-info/top_level.txt
SSD_python-0.0.1.dist-info/RECORD
