Metadata-Version: 2.1
Name: SSD-python
Version: 0.0.1
Summary: Python interface for Supervised Sparse Decomposition (SSD)
Author: Bowen Jin
Author-email: bowenjin@stu.njmu.edu.cn
Requires-Python: >=3.9.0
License-File: LICENSE
Requires-Dist: numpy >=1.21.3
Requires-Dist: scipy >=1.5
Requires-Dist: torch
Requires-Dist: spams
